orb/__init__.py
ls_orb-0.1.0.dist-info/METADATA
ls_orb-0.1.0.dist-info/WHEEL
ls_orb-0.1.0.dist-info/top_level.txt
ls_orb-0.1.0.dist-info/RECORD
